dice_score_3d/__init__.py
dice_score_3d/main.py
dice_score_3d/metrics.py
dice_score_3d/reader.py
dice_score_3d-1.1.2.dist-info/licenses/LICENSE
dice_score_3d-1.1.2.dist-info/METADATA
dice_score_3d-1.1.2.dist-info/WHEEL
dice_score_3d-1.1.2.dist-info/entry_points.txt
dice_score_3d-1.1.2.dist-info/top_level.txt
dice_score_3d-1.1.2.dist-info/RECORD
