Metadata-Version: 2.4
Name: dice-score-3d
Version: 1.1.2
Summary: Utility for calculating the Dice Similarity Coefficient (DSC) for 3D segmentation masks.
Author-email: George Stoica <george.stoica@info.uaic.ro>
Maintainer-email: George Stoica <george.stoica@info.uaic.ro>
License: MIT License
Project-URL: Repository, https://github.com/ancestor-mithril/dice-score-3d
Project-URL: Issues, https://github.com/ancestor-mithril/dice-score-3d/issues
Keywords: image segmentation,dice similarity coefficient,dice score
Classifier: Development Status :: 5 - Production/Stable
Classifier: Intended Audience :: Developers
Classifier: Intended Audience :: Science/Research
Classifier: Intended Audience :: Healthcare Industry
Classifier: License :: OSI Approved :: MIT License
Classifier: Operating System :: OS Independent
Classifier: Programming Language :: Python :: 3
Classifier: Topic :: Scientific/Engineering :: Medical Science Apps.
Requires-Python: >=3.7
License-File: LICENSE
Requires-Dist: numpy
Requires-Dist: SimpleITK
Requires-Dist: tqdm
Provides-Extra: dev
Requires-Dist: pytest; extra == "dev"
Requires-Dist: flake8; extra == "dev"
Dynamic: license-file
